{"id":"cube_1_-4_-2","label":"Gaia DR3 cube 1_-4_-2","epoch":"J2016.0","source":"Gaia DR3 gaia_source; filtrat per paral.laxi fiable i magnitud G","stars":[{"name":"Gaia DR3 4181678569973511040","sourceId":"4181678569973511040","ra":295.1810795,"dec":-16.2934956,"distancePc":76.96958,"spectral":"Gaia","mag":4.9789,"color":"#ffd29a","note":"Gaia DR3; distancia estimada amb paral.laxi"},{"name":"Gaia DR3 6766104084405895040","sourceId":"6766104084405895040","ra":292.4675562,"dec":-26.9858182,"distancePc":84.70645,"spectral":"Gaia","mag":5.2051,"color":"#ffd29a","note":"Gaia DR3; distancia estimada amb paral.laxi"},{"name":"Gaia DR3 6870272159619885952","sourceId":"6870272159619885952","ra":298.050007,"dec":-19.0452722,"distancePc":88.28534,"spectral":"Gaia","mag":5.6002,"color":"#ffd29a","note":"Gaia DR3; distancia estimada amb paral.laxi"},{"name":"Gaia DR3 6767920580693895808","sourceId":"6767920580693895808","ra":294.0069212,"dec":-24.7191969,"distancePc":81.17245,"spectral":"Gaia","mag":5.6206,"color":"#e4f0ff","note":"Gaia DR3; distancia estimada amb paral.laxi"},{"name":"Gaia DR3 6869593898383897600","sourceId":"6869593898383897600","ra":294.1087538,"dec":-18.8529796,"distancePc":78.64993,"spectral":"Gaia","mag":6.0815,"color":"#fff2c8","note":"Gaia DR3; distancia estimada amb paral.laxi"},{"name":"Gaia DR3 4075669603079159680","sourceId":"4075669603079159680","ra":284.6034864,"dec":-22.5294387,"distancePc":87.34485,"spectral":"Gaia","mag":6.1325,"color":"#e4f0ff","note":"Gaia DR3; distancia estimada amb paral.laxi"},{"name":"Gaia DR3 4082719809063565696","sourceId":"4082719809063565696","ra":290.6679563,"dec":-20.6433742,"distancePc":75.37697,"spectral":"Gaia","mag":6.3008,"color":"#ffd29a","note":"Gaia DR3; distancia estimada amb paral.laxi"},{"name":"Gaia DR3 4080503709018054400","sourceId":"4080503709018054400","ra":287.1851812,"dec":-23.1903447,"distancePc":80.0572,"spectral":"Gaia","mag":6.4256,"color":"#ffd29a","note":"Gaia DR3; distancia estimada amb paral.laxi"},{"name":"Gaia DR3 6867257298735553792","sourceId":"6867257298735553792","ra":298.8504228,"dec":-19.2928998,"distancePc":86.26237,"spectral":"Gaia","mag":6.7964,"color":"#fff2c8","note":"Gaia DR3; distancia estimada amb paral.laxi"},{"name":"Gaia DR3 4087081880937346816","sourceId":"4087081880937346816","ra":287.2377877,"dec":-18.6827755,"distancePc":77.83516,"spectral":"Gaia","mag":6.8765,"color":"#fff2c8","note":"Gaia DR3; distancia estimada amb paral.laxi"},{"name":"Gaia DR3 6877310133547083392","sourceId":"6877310133547083392","ra":300.1243253,"dec":-15.8870679,"distancePc":75.68527,"spectral":"Gaia","mag":7.0965,"color":"#fff2c8","note":"Gaia DR3; distancia estimada amb paral.laxi"},{"name":"Gaia DR3 4180762608077527040","sourceId":"4180762608077527040","ra":290.4231666,"dec":-17.2456068,"distancePc":74.56591,"spectral":"Gaia","mag":7.2859,"color":"#fff2c8","note":"Gaia DR3; distancia estimada amb paral.laxi"},{"name":"Gaia DR3 6866303987792105856","sourceId":"6866303987792105856","ra":302.3895387,"dec":-20.5939852,"distancePc":77.89717,"spectral":"Gaia","mag":7.3816,"color":"#fff2c8","note":"Gaia DR3; distancia estimada amb paral.laxi"},{"name":"Gaia DR3 6867554613549892864","sourceId":"6867554613549892864","ra":300.7289882,"dec":-18.5465848,"distancePc":80.70285,"spectral":"Gaia","mag":7.4904,"color":"#fff2c8","note":"Gaia DR3; distancia estimada amb paral.laxi"},{"name":"Gaia DR3 6754228499831566848","sourceId":"6754228499831566848","ra":298.9671953,"dec":-26.550005,"distancePc":81.23076,"spectral":"Gaia","mag":7.5915,"color":"#fff2c8","note":"Gaia DR3; distancia estimada amb paral.laxi"},{"name":"Gaia DR3 4185205008718146048","sourceId":"4185205008718146048","ra":288.3578735,"dec":-14.4473182,"distancePc":84.20569,"spectral":"Gaia","mag":7.6778,"color":"#fff2c8","note":"Gaia DR3; distancia estimada amb paral.laxi"},{"name":"Gaia DR3 6759168021467638912","sourceId":"6759168021467638912","ra":287.6736921,"dec":-29.8140693,"distancePc":77.06844,"spectral":"Gaia","mag":7.8756,"color":"#fff2c8","note":"Gaia DR3; distancia estimada amb paral.laxi"}]}
