{"id":"cube_0_1_1","label":"Gaia DR3 cube 0_1_1","epoch":"J2016.0","source":"Gaia DR3 gaia_source; filtrat per paral.laxi fiable i magnitud G","stars":[{"name":"Gaia DR3 188206261484037504","sourceId":"188206261484037504","ra":78.3570577,"dec":38.4841633,"distancePc":49.74739,"spectral":"Gaia","mag":4.732,"color":"#e4f0ff","note":"Gaia DR3; distancia estimada amb paral.laxi"},{"name":"Gaia DR3 198776553956317312","sourceId":"198776553956317312","ra":74.814461,"dec":37.8898108,"distancePc":49.40725,"spectral":"Gaia","mag":4.98,"color":"#e4f0ff","note":"Gaia DR3; distancia estimada amb paral.laxi"},{"name":"Gaia DR3 250437313946591360","sourceId":"250437313946591360","ra":59.1528147,"dec":50.6948,"distancePc":38.14316,"spectral":"Gaia","mag":5.1677,"color":"#fff2c8","note":"Gaia DR3; distancia estimada amb paral.laxi"},{"name":"Gaia DR3 241996500618616960","sourceId":"241996500618616960","ra":53.1090734,"dec":46.056529,"distancePc":36.95776,"spectral":"Gaia","mag":5.1921,"color":"#fff2c8","note":"Gaia DR3; distancia estimada amb paral.laxi"},{"name":"Gaia DR3 212816321010824064","sourceId":"212816321010824064","ra":77.6792125,"dec":46.9614033,"distancePc":49.77661,"spectral":"Gaia","mag":5.5649,"color":"#fff2c8","note":"Gaia DR3; distancia estimada amb paral.laxi"},{"name":"Gaia DR3 172817599818083712","sourceId":"172817599818083712","ra":66.1563228,"dec":33.9594009,"distancePc":42.03029,"spectral":"Gaia","mag":5.6812,"color":"#fff2c8","note":"Gaia DR3; distancia estimada amb paral.laxi"},{"name":"Gaia DR3 225643223661003392","sourceId":"225643223661003392","ra":62.0635641,"dec":37.7266258,"distancePc":45.29353,"spectral":"Gaia","mag":5.8269,"color":"#ffd29a","note":"Gaia DR3; distancia estimada amb paral.laxi"},{"name":"Gaia DR3 435646474233078144","sourceId":"435646474233078144","ra":50.4701174,"dec":49.0706246,"distancePc":43.91109,"spectral":"Gaia","mag":5.8339,"color":"#fff2c8","note":"Gaia DR3; distancia estimada amb paral.laxi"},{"name":"Gaia DR3 276284736371675648","sourceId":"276284736371675648","ra":62.3431875,"dec":54.8284561,"distancePc":43.48636,"spectral":"Gaia","mag":6.1517,"color":"#fff2c8","note":"Gaia DR3; distancia estimada amb paral.laxi"},{"name":"Gaia DR3 269413338450710016","sourceId":"269413338450710016","ra":83.1417451,"dec":57.2200719,"distancePc":43.20348,"spectral":"Gaia","mag":6.3058,"color":"#fff2c8","note":"Gaia DR3; distancia estimada amb paral.laxi"},{"name":"Gaia DR3 199579506681904128","sourceId":"199579506681904128","ra":71.148341,"dec":38.254991,"distancePc":51.85673,"spectral":"Gaia","mag":6.5318,"color":"#ffd29a","note":"Gaia DR3; distancia estimada amb paral.laxi"},{"name":"Gaia DR3 237507744398899200","sourceId":"237507744398899200","ra":54.7371354,"dec":42.5377055,"distancePc":45.05434,"spectral":"Gaia","mag":6.5971,"color":"#fff2c8","note":"Gaia DR3; distancia estimada amb paral.laxi"},{"name":"Gaia DR3 178112641659509760","sourceId":"178112641659509760","ra":68.0720505,"dec":37.0432123,"distancePc":45.38568,"spectral":"Gaia","mag":6.6685,"color":"#fff2c8","note":"Gaia DR3; distancia estimada amb paral.laxi"},{"name":"Gaia DR3 251738448519542144","sourceId":"251738448519542144","ra":58.9036279,"dec":52.2273044,"distancePc":39.55952,"spectral":"Gaia","mag":6.6869,"color":"#fff2c8","note":"Gaia DR3; distancia estimada amb paral.laxi"},{"name":"Gaia DR3 215521394490842624","sourceId":"215521394490842624","ra":86.3751401,"dec":52.1603555,"distancePc":46.78915,"spectral":"Gaia","mag":6.6971,"color":"#ffd29a","note":"Gaia DR3; distancia estimada amb paral.laxi"},{"name":"Gaia DR3 169149766470219520","sourceId":"169149766470219520","ra":62.4122359,"dec":31.6524443,"distancePc":40.90633,"spectral":"Gaia","mag":6.7598,"color":"#fff2c8","note":"Gaia DR3; distancia estimada amb paral.laxi"},{"name":"Gaia DR3 254503754623418240","sourceId":"254503754623418240","ra":72.9339356,"dec":45.8316559,"distancePc":31.02662,"spectral":"Gaia","mag":6.8037,"color":"#fff2c8","note":"Gaia DR3; distancia estimada amb paral.laxi"},{"name":"Gaia DR3 271083015576372096","sourceId":"271083015576372096","ra":66.1366715,"dec":50.8448866,"distancePc":49.20576,"spectral":"Gaia","mag":6.8519,"color":"#fff2c8","note":"Gaia DR3; distancia estimada amb paral.laxi"},{"name":"Gaia DR3 227589290522957440","sourceId":"227589290522957440","ra":65.5008772,"dec":39.9334443,"distancePc":53.9998,"spectral":"Gaia","mag":6.8874,"color":"#fff2c8","note":"Gaia DR3; distancia estimada amb paral.laxi"},{"name":"Gaia DR3 199279271288398720","sourceId":"199279271288398720","ra":74.5544971,"dec":40.0564152,"distancePc":48.38064,"spectral":"Gaia","mag":7.1222,"color":"#fff2c8","note":"Gaia DR3; distancia estimada amb paral.laxi"},{"name":"Gaia DR3 226778843075710976","sourceId":"226778843075710976","ra":61.0304142,"dec":39.509292,"distancePc":33.98544,"spectral":"Gaia","mag":7.1809,"color":"#ffd29a","note":"Gaia DR3; distancia estimada amb paral.laxi"},{"name":"Gaia DR3 194405990937384064","sourceId":"194405990937384064","ra":84.2799914,"dec":41.8281115,"distancePc":43.78129,"spectral":"Gaia","mag":7.2615,"color":"#fff2c8","note":"Gaia DR3; distancia estimada amb paral.laxi"},{"name":"Gaia DR3 243285849800883456","sourceId":"243285849800883456","ra":55.9509337,"dec":42.6022128,"distancePc":45.55424,"spectral":"Gaia","mag":7.3357,"color":"#fff2c8","note":"Gaia DR3; distancia estimada amb paral.laxi"},{"name":"Gaia DR3 233223703502612352","sourceId":"233223703502612352","ra":62.0575497,"dec":44.6622459,"distancePc":32.35714,"spectral":"Gaia","mag":7.5552,"color":"#ffd29a","note":"Gaia DR3; distancia estimada amb paral.laxi"},{"name":"Gaia DR3 267971809987544064","sourceId":"267971809987544064","ra":82.8695342,"dec":54.6530791,"distancePc":40.87256,"spectral":"Gaia","mag":7.56,"color":"#fff2c8","note":"Gaia DR3; distancia estimada amb paral.laxi"},{"name":"Gaia DR3 262176455996527872","sourceId":"262176455996527872","ra":80.4572074,"dec":51.4852385,"distancePc":48.88193,"spectral":"Gaia","mag":7.6003,"color":"#ffd29a","note":"Gaia DR3; distancia estimada amb paral.laxi"},{"name":"Gaia DR3 198776553956316928","sourceId":"198776553956316928","ra":74.8145863,"dec":37.8911239,"distancePc":48.92511,"spectral":"Gaia","mag":7.6848,"color":"#fff2c8","note":"Gaia DR3; distancia estimada amb paral.laxi"},{"name":"Gaia DR3 181312735893067008","sourceId":"181312735893067008","ra":77.7456985,"dec":32.0389064,"distancePc":44.98007,"spectral":"Gaia","mag":7.8772,"color":"#ffd29a","note":"Gaia DR3; distancia estimada amb paral.laxi"},{"name":"Gaia DR3 272026980672350336","sourceId":"272026980672350336","ra":66.6097133,"dec":52.5043759,"distancePc":44.3874,"spectral":"Gaia","mag":7.9063,"color":"#ffd29a","note":"Gaia DR3; distancia estimada amb paral.laxi"},{"name":"Gaia DR3 201487468594945408","sourceId":"201487468594945408","ra":77.4399179,"dec":42.6709306,"distancePc":31.01432,"spectral":"Gaia","mag":7.9391,"color":"#ffd29a","note":"Gaia DR3; distancia estimada amb paral.laxi"}]}
