{"id":"cube_2_-1_-1","label":"Gaia DR3 cube 2_-1_-1","epoch":"J2016.0","source":"Gaia DR3 gaia_source; filtrat per paral.laxi fiable i magnitud G","stars":[{"name":"Gaia DR3 2392584791494639744","sourceId":"2392584791494639744","ra":350.7420346,"dec":-20.1010167,"distancePc":50.36323,"spectral":"Gaia","mag":3.627,"color":"#ff9f73","note":"Gaia DR3; distancia estimada amb paral.laxi"},{"name":"Gaia DR3 2630155547353593216","sourceId":"2630155547353593216","ra":348.9745549,"dec":-9.0878102,"distancePc":45.26451,"spectral":"Gaia","mag":3.9247,"color":"#ffd29a","note":"Gaia DR3; distancia estimada amb paral.laxi"},{"name":"Gaia DR3 2653884210872467200","sourceId":"2653884210872467200","ra":338.839486,"dec":-0.117742,"distancePc":54.43402,"spectral":"Gaia","mag":4.0255,"color":"#e4f0ff","note":"Gaia DR3; distancia estimada amb paral.laxi"},{"name":"Gaia DR3 2419885149815948416","sourceId":"2419885149815948416","ra":355.6810581,"dec":-14.5451999,"distancePc":47.85875,"spectral":"Gaia","mag":4.4737,"color":"#e4f0ff","note":"Gaia DR3; distancia estimada amb paral.laxi"},{"name":"Gaia DR3 2633314341181013376","sourceId":"2633314341181013376","ra":352.384471,"dec":-4.5337745,"distancePc":45.48971,"spectral":"Gaia","mag":5.9697,"color":"#ffd29a","note":"Gaia DR3; distancia estimada amb paral.laxi"},{"name":"Gaia DR3 2634027752428716928","sourceId":"2634027752428716928","ra":350.0673126,"dec":-3.9196175,"distancePc":46.81279,"spectral":"Gaia","mag":6.5211,"color":"#fff2c8","note":"Gaia DR3; distancia estimada amb paral.laxi"},{"name":"Gaia DR3 2391133607944627840","sourceId":"2391133607944627840","ra":356.5059153,"dec":-18.6796391,"distancePc":48.89138,"spectral":"Gaia","mag":6.5547,"color":"#fff2c8","note":"Gaia DR3; distancia estimada amb paral.laxi"},{"name":"Gaia DR3 2631031170926210944","sourceId":"2631031170926210944","ra":349.2470218,"dec":-7.1605789,"distancePc":48.41917,"spectral":"Gaia","mag":6.6031,"color":"#fff2c8","note":"Gaia DR3; distancia estimada amb paral.laxi"},{"name":"Gaia DR3 2403854545161475840","sourceId":"2403854545161475840","ra":341.8554038,"dec":-17.5507597,"distancePc":45.27409,"spectral":"Gaia","mag":6.685,"color":"#fff2c8","note":"Gaia DR3; distancia estimada amb paral.laxi"},{"name":"Gaia DR3 2608919785932997248","sourceId":"2608919785932997248","ra":340.0340402,"dec":-9.3590341,"distancePc":53.39908,"spectral":"Gaia","mag":6.7621,"color":"#fff2c8","note":"Gaia DR3; distancia estimada amb paral.laxi"},{"name":"Gaia DR3 2629041948233065216","sourceId":"2629041948233065216","ra":336.5600427,"dec":-2.7893353,"distancePc":48.32125,"spectral":"Gaia","mag":6.8419,"color":"#fff2c8","note":"Gaia DR3; distancia estimada amb paral.laxi"},{"name":"Gaia DR3 2639405120203115776","sourceId":"2639405120203115776","ra":353.8113515,"dec":-3.8536212,"distancePc":53.78314,"spectral":"Gaia","mag":7.1202,"color":"#fff2c8","note":"Gaia DR3; distancia estimada amb paral.laxi"},{"name":"Gaia DR3 2419460360370951936","sourceId":"2419460360370951936","ra":358.9541557,"dec":-13.9664553,"distancePc":50.2963,"spectral":"Gaia","mag":7.1891,"color":"#fff2c8","note":"Gaia DR3; distancia estimada amb paral.laxi"},{"name":"Gaia DR3 2393516004828451712","sourceId":"2393516004828451712","ra":350.967815,"dec":-17.7894593,"distancePc":60.023,"spectral":"Gaia","mag":7.4003,"color":"#fff2c8","note":"Gaia DR3; distancia estimada amb paral.laxi"},{"name":"Gaia DR3 2418452383086016384","sourceId":"2418452383086016384","ra":357.0385053,"dec":-16.6993558,"distancePc":56.92561,"spectral":"Gaia","mag":7.4385,"color":"#fff2c8","note":"Gaia DR3; distancia estimada amb paral.laxi"},{"name":"Gaia DR3 2440578577126302336","sourceId":"2440578577126302336","ra":355.4640585,"dec":-5.9862535,"distancePc":42.02474,"spectral":"Gaia","mag":7.5338,"color":"#ffd29a","note":"Gaia DR3; distancia estimada amb paral.laxi"},{"name":"Gaia DR3 2391838429257482496","sourceId":"2391838429257482496","ra":351.470726,"dec":-20.616817,"distancePc":46.93209,"spectral":"Gaia","mag":7.6072,"color":"#fff2c8","note":"Gaia DR3; distancia estimada amb paral.laxi"},{"name":"Gaia DR3 2648705785983069056","sourceId":"2648705785983069056","ra":344.3582136,"dec":-3.1579797,"distancePc":47.89988,"spectral":"Gaia","mag":7.6092,"color":"#fff2c8","note":"Gaia DR3; distancia estimada amb paral.laxi"},{"name":"Gaia DR3 2650902026099857920","sourceId":"2650902026099857920","ra":345.7837966,"dec":-0.430383,"distancePc":54.96409,"spectral":"Gaia","mag":7.6493,"color":"#fff2c8","note":"Gaia DR3; distancia estimada amb paral.laxi"},{"name":"Gaia DR3 2403698135336770688","sourceId":"2403698135336770688","ra":344.9449187,"dec":-16.3994056,"distancePc":57.68782,"spectral":"Gaia","mag":7.6619,"color":"#fff2c8","note":"Gaia DR3; distancia estimada amb paral.laxi"},{"name":"Gaia DR3 2434956499296915200","sourceId":"2434956499296915200","ra":359.391719,"dec":-9.6481701,"distancePc":51.15866,"spectral":"Gaia","mag":7.7408,"color":"#ffd29a","note":"Gaia DR3; distancia estimada amb paral.laxi"},{"name":"Gaia DR3 2422003496407131776","sourceId":"2422003496407131776","ra":359.7623756,"dec":-11.9385845,"distancePc":52.01597,"spectral":"Gaia","mag":7.9197,"color":"#fff2c8","note":"Gaia DR3; distancia estimada amb paral.laxi"}]}
