{"id":"cube_-1_2_2","label":"Gaia DR3 cube -1_2_2","epoch":"J2016.0","source":"Gaia DR3 gaia_source; filtrat per paral.laxi fiable i magnitud G","stars":[{"name":"Gaia DR3 953838195501646848","sourceId":"953838195501646848","ra":104.4044786,"dec":45.0940788,"distancePc":69.41938,"spectral":"Gaia","mag":4.8726,"color":"#e4f0ff","note":"Gaia DR3; distancia estimada amb paral.laxi"},{"name":"Gaia DR3 960883900373695744","sourceId":"960883900373695744","ra":90.8255148,"dec":42.9108993,"distancePc":65.58353,"spectral":"Gaia","mag":5.8123,"color":"#ffd29a","note":"Gaia DR3; distancia estimada amb paral.laxi"},{"name":"Gaia DR3 968597489838610432","sourceId":"968597489838610432","ra":94.3940798,"dec":46.4240021,"distancePc":76.29494,"spectral":"Gaia","mag":6.4772,"color":"#fff2c8","note":"Gaia DR3; distancia estimada amb paral.laxi"},{"name":"Gaia DR3 977912105670843392","sourceId":"977912105670843392","ra":108.3037052,"dec":47.6064719,"distancePc":62.97557,"spectral":"Gaia","mag":6.6894,"color":"#fff2c8","note":"Gaia DR3; distancia estimada amb paral.laxi"},{"name":"Gaia DR3 977695055203412480","sourceId":"977695055203412480","ra":105.9952806,"dec":47.050005,"distancePc":73.4952,"spectral":"Gaia","mag":6.878,"color":"#fff2c8","note":"Gaia DR3; distancia estimada amb paral.laxi"},{"name":"Gaia DR3 977898499214591744","sourceId":"977898499214591744","ra":108.4057896,"dec":47.2668065,"distancePc":64.18951,"spectral":"Gaia","mag":6.9259,"color":"#fff2c8","note":"Gaia DR3; distancia estimada amb paral.laxi"},{"name":"Gaia DR3 945553341027200256","sourceId":"945553341027200256","ra":100.1767392,"dec":40.1686232,"distancePc":73.65564,"spectral":"Gaia","mag":7.0313,"color":"#fff2c8","note":"Gaia DR3; distancia estimada amb paral.laxi"},{"name":"Gaia DR3 967658369468831744","sourceId":"967658369468831744","ra":96.9097968,"dec":48.7770425,"distancePc":72.10148,"spectral":"Gaia","mag":7.1799,"color":"#fff2c8","note":"Gaia DR3; distancia estimada amb paral.laxi"},{"name":"Gaia DR3 957207580165891072","sourceId":"957207580165891072","ra":99.6525603,"dec":40.3356024,"distancePc":64.53651,"spectral":"Gaia","mag":7.3292,"color":"#ffd29a","note":"Gaia DR3; distancia estimada amb paral.laxi"},{"name":"Gaia DR3 950689984474189184","sourceId":"950689984474189184","ra":104.0614469,"dec":40.5367263,"distancePc":71.61606,"spectral":"Gaia","mag":7.4107,"color":"#fff2c8","note":"Gaia DR3; distancia estimada amb paral.laxi"},{"name":"Gaia DR3 974328110082100992","sourceId":"974328110082100992","ra":109.5056264,"dec":45.128347,"distancePc":70.26148,"spectral":"Gaia","mag":7.5098,"color":"#fff2c8","note":"Gaia DR3; distancia estimada amb paral.laxi"},{"name":"Gaia DR3 933776197103349632","sourceId":"933776197103349632","ra":116.266809,"dec":48.3947283,"distancePc":67.94416,"spectral":"Gaia","mag":7.5856,"color":"#fff2c8","note":"Gaia DR3; distancia estimada amb paral.laxi"},{"name":"Gaia DR3 949380912801973248","sourceId":"949380912801973248","ra":108.9780957,"dec":41.9293359,"distancePc":67.58623,"spectral":"Gaia","mag":7.686,"color":"#fff2c8","note":"Gaia DR3; distancia estimada amb paral.laxi"},{"name":"Gaia DR3 995044107446214784","sourceId":"995044107446214784","ra":99.0092185,"dec":55.692241,"distancePc":72.2922,"spectral":"Gaia","mag":7.7195,"color":"#fff2c8","note":"Gaia DR3; distancia estimada amb paral.laxi"},{"name":"Gaia DR3 951601479613983104","sourceId":"951601479613983104","ra":102.9616704,"dec":41.5766225,"distancePc":63.78244,"spectral":"Gaia","mag":7.7322,"color":"#fff2c8","note":"Gaia DR3; distancia estimada amb paral.laxi"},{"name":"Gaia DR3 950770145743750400","sourceId":"950770145743750400","ra":103.5477401,"dec":40.8897217,"distancePc":75.60196,"spectral":"Gaia","mag":7.7613,"color":"#fff2c8","note":"Gaia DR3; distancia estimada amb paral.laxi"},{"name":"Gaia DR3 952349594196438528","sourceId":"952349594196438528","ra":102.2043102,"dec":43.8348075,"distancePc":83.35029,"spectral":"Gaia","mag":7.8393,"color":"#fff2c8","note":"Gaia DR3; distancia estimada amb paral.laxi"},{"name":"Gaia DR3 963572309382205440","sourceId":"963572309382205440","ra":90.6206971,"dec":46.6446907,"distancePc":82.28286,"spectral":"Gaia","mag":7.9058,"color":"#fff2c8","note":"Gaia DR3; distancia estimada amb paral.laxi"}]}
