{"id":"cube_-2_-3_3","label":"Gaia DR3 cube -2_-3_3","epoch":"J2016.0","source":"Gaia DR3 gaia_source; filtrat per paral.laxi fiable i magnitud G","stars":[{"name":"Gaia DR3 1596640009092360320","sourceId":"1596640009092360320","ra":235.7110216,"dec":52.3610315,"distancePc":91.79105,"spectral":"Gaia","mag":5.4631,"color":"#e4f0ff","note":"Gaia DR3; distancia estimada amb paral.laxi"},{"name":"Gaia DR3 1598411047445960320","sourceId":"1598411047445960320","ra":238.0687902,"dec":55.8269534,"distancePc":94.51764,"spectral":"Gaia","mag":5.5863,"color":"#ffd29a","note":"Gaia DR3; distancia estimada amb paral.laxi"},{"name":"Gaia DR3 1601127253483302528","sourceId":"1601127253483302528","ra":232.2366997,"dec":55.1950988,"distancePc":93.79935,"spectral":"Gaia","mag":6.4337,"color":"#e4f0ff","note":"Gaia DR3; distancia estimada amb paral.laxi"},{"name":"Gaia DR3 1411412397625950848","sourceId":"1411412397625950848","ra":247.5248217,"dec":48.9608326,"distancePc":94.64073,"spectral":"Gaia","mag":6.436,"color":"#e4f0ff","note":"Gaia DR3; distancia estimada amb paral.laxi"},{"name":"Gaia DR3 1427909160851355392","sourceId":"1427909160851355392","ra":243.9470937,"dec":53.236396,"distancePc":88.03965,"spectral":"Gaia","mag":6.8521,"color":"#fff2c8","note":"Gaia DR3; distancia estimada amb paral.laxi"},{"name":"Gaia DR3 1395620043396589184","sourceId":"1395620043396589184","ra":231.3722318,"dec":45.94804,"distancePc":85.53976,"spectral":"Gaia","mag":7.1508,"color":"#fff2c8","note":"Gaia DR3; distancia estimada amb paral.laxi"},{"name":"Gaia DR3 1598736193650220800","sourceId":"1598736193650220800","ra":236.6606931,"dec":56.7701801,"distancePc":87.74147,"spectral":"Gaia","mag":7.5075,"color":"#ffd29a","note":"Gaia DR3; distancia estimada amb paral.laxi"}]}
