{"id":"cube_-2_-3_-2","label":"Gaia DR3 cube -2_-3_-2","epoch":"J2016.0","source":"Gaia DR3 gaia_source; filtrat per paral.laxi fiable i magnitud G","stars":[{"name":"Gaia DR3 6210176643031265920","sourceId":"6210176643031265920","ra":234.2559551,"dec":-28.1350584,"distancePc":64.40534,"spectral":"Gaia","mag":3.1413,"color":"#ff9f73","note":"Gaia DR3; distancia estimada amb paral.laxi"},{"name":"Gaia DR3 6015150905501817472","sourceId":"6015150905501817472","ra":237.7396868,"dec":-33.6273256,"distancePc":62.87767,"spectral":"Gaia","mag":3.9584,"color":"#e4f0ff","note":"Gaia DR3; distancia estimada amb paral.laxi"},{"name":"Gaia DR3 6244910765107054848","sourceId":"6244910765107054848","ra":246.0256197,"dec":-20.0375262,"distancePc":59.45172,"spectral":"Gaia","mag":4.2126,"color":"#ffd29a","note":"Gaia DR3; distancia estimada amb paral.laxi"},{"name":"Gaia DR3 6013425703029987712","sourceId":"6013425703029987712","ra":234.9416133,"dec":-34.4119708,"distancePc":67.88103,"spectral":"Gaia","mag":4.3852,"color":"#ffd29a","note":"Gaia DR3; distancia estimada amb paral.laxi"},{"name":"Gaia DR3 6043646879640103936","sourceId":"6043646879640103936","ra":240.8355947,"dec":-25.8654121,"distancePc":66.87528,"spectral":"Gaia","mag":4.5705,"color":"#ff9f73","note":"Gaia DR3; distancia estimada amb paral.laxi"},{"name":"Gaia DR3 6012174802400278016","sourceId":"6012174802400278016","ra":239.2229376,"dec":-33.9662834,"distancePc":66.56476,"spectral":"Gaia","mag":5.0795,"color":"#e4f0ff","note":"Gaia DR3; distancia estimada amb paral.laxi"},{"name":"Gaia DR3 6012174836760016512","sourceId":"6012174836760016512","ra":239.2255272,"dec":-33.9644431,"distancePc":64.50977,"spectral":"Gaia","mag":5.6023,"color":"#e4f0ff","note":"Gaia DR3; distancia estimada amb paral.laxi"},{"name":"Gaia DR3 5998675582756950272","sourceId":"5998675582756950272","ra":241.8178311,"dec":-36.7558837,"distancePc":65.3992,"spectral":"Gaia","mag":5.6138,"color":"#fff2c8","note":"Gaia DR3; distancia estimada amb paral.laxi"},{"name":"Gaia DR3 6045581642143801600","sourceId":"6045581642143801600","ra":247.8450314,"dec":-26.5377961,"distancePc":69.00995,"spectral":"Gaia","mag":5.783,"color":"#ffd29a","note":"Gaia DR3; distancia estimada amb paral.laxi"},{"name":"Gaia DR3 6036433911563424640","sourceId":"6036433911563424640","ra":240.8929655,"dec":-32.0006573,"distancePc":57.20227,"spectral":"Gaia","mag":5.8806,"color":"#fff2c8","note":"Gaia DR3; distancia estimada amb paral.laxi"},{"name":"Gaia DR3 6040691564179511040","sourceId":"6040691564179511040","ra":238.0526612,"dec":-29.886972,"distancePc":69.69884,"spectral":"Gaia","mag":6.1394,"color":"#ffd29a","note":"Gaia DR3; distancia estimada amb paral.laxi"},{"name":"Gaia DR3 6253612575011062400","sourceId":"6253612575011062400","ra":232.6510709,"dec":-20.7286821,"distancePc":70.06547,"spectral":"Gaia","mag":6.1806,"color":"#e4f0ff","note":"Gaia DR3; distancia estimada amb paral.laxi"},{"name":"Gaia DR3 6016565186686012544","sourceId":"6016565186686012544","ra":236.0171008,"dec":-31.6037066,"distancePc":75.32172,"spectral":"Gaia","mag":6.3833,"color":"#ffd29a","note":"Gaia DR3; distancia estimada amb paral.laxi"},{"name":"Gaia DR3 6022803300287482112","sourceId":"6022803300287482112","ra":242.5024803,"dec":-35.6428902,"distancePc":67.91985,"spectral":"Gaia","mag":7.0186,"color":"#fff2c8","note":"Gaia DR3; distancia estimada amb paral.laxi"},{"name":"Gaia DR3 6041555093123155840","sourceId":"6041555093123155840","ra":239.306781,"dec":-27.6427973,"distancePc":65.78483,"spectral":"Gaia","mag":7.1963,"color":"#fff2c8","note":"Gaia DR3; distancia estimada amb paral.laxi"},{"name":"Gaia DR3 6236729848841353472","sourceId":"6236729848841353472","ra":236.4572128,"dec":-24.7170724,"distancePc":76.54042,"spectral":"Gaia","mag":7.2584,"color":"#ffd29a","note":"Gaia DR3; distancia estimada amb paral.laxi"},{"name":"Gaia DR3 6036561970315289344","sourceId":"6036561970315289344","ra":242.2963057,"dec":-32.1017036,"distancePc":54.70008,"spectral":"Gaia","mag":7.3194,"color":"#fff2c8","note":"Gaia DR3; distancia estimada amb paral.laxi"},{"name":"Gaia DR3 6240300684653071488","sourceId":"6240300684653071488","ra":237.6660223,"dec":-23.2583961,"distancePc":52.92563,"spectral":"Gaia","mag":7.3364,"color":"#fff2c8","note":"Gaia DR3; distancia estimada amb paral.laxi"},{"name":"Gaia DR3 6049090011941029888","sourceId":"6049090011941029888","ra":247.2454596,"dec":-24.5388603,"distancePc":64.16983,"spectral":"Gaia","mag":7.4068,"color":"#ffd29a","note":"Gaia DR3; distancia estimada amb paral.laxi"},{"name":"Gaia DR3 6253930780541563392","sourceId":"6253930780541563392","ra":234.977303,"dec":-19.7691874,"distancePc":66.67152,"spectral":"Gaia","mag":7.5274,"color":"#fff2c8","note":"Gaia DR3; distancia estimada amb paral.laxi"},{"name":"Gaia DR3 6260939479977516544","sourceId":"6260939479977516544","ra":236.4599498,"dec":-16.9508061,"distancePc":74.65552,"spectral":"Gaia","mag":7.5537,"color":"#fff2c8","note":"Gaia DR3; distancia estimada amb paral.laxi"},{"name":"Gaia DR3 6253930780545661952","sourceId":"6253930780545661952","ra":234.9776878,"dec":-19.7688607,"distancePc":66.50877,"spectral":"Gaia","mag":7.5572,"color":"#fff2c8","note":"Gaia DR3; distancia estimada amb paral.laxi"},{"name":"Gaia DR3 6049606095214667008","sourceId":"6049606095214667008","ra":243.9450907,"dec":-25.1220209,"distancePc":73.51393,"spectral":"Gaia","mag":7.563,"color":"#ffd29a","note":"Gaia DR3; distancia estimada amb paral.laxi"},{"name":"Gaia DR3 6233152175445659264","sourceId":"6233152175445659264","ra":237.0939245,"dec":-28.7892505,"distancePc":73.63089,"spectral":"Gaia","mag":7.5673,"color":"#fff2c8","note":"Gaia DR3; distancia estimada amb paral.laxi"},{"name":"Gaia DR3 6021767663398535936","sourceId":"6021767663398535936","ra":244.588357,"dec":-36.5657782,"distancePc":63.75752,"spectral":"Gaia","mag":7.6358,"color":"#fff2c8","note":"Gaia DR3; distancia estimada amb paral.laxi"},{"name":"Gaia DR3 6251810544171864704","sourceId":"6251810544171864704","ra":232.6780753,"dec":-21.8784735,"distancePc":69.1932,"spectral":"Gaia","mag":7.6459,"color":"#fff2c8","note":"Gaia DR3; distancia estimada amb paral.laxi"},{"name":"Gaia DR3 6241692563292234880","sourceId":"6241692563292234880","ra":236.834034,"dec":-20.4699459,"distancePc":67.58015,"spectral":"Gaia","mag":7.7113,"color":"#fff2c8","note":"Gaia DR3; distancia estimada amb paral.laxi"},{"name":"Gaia DR3 6250226147909726464","sourceId":"6250226147909726464","ra":239.490441,"dec":-17.0904911,"distancePc":68.713,"spectral":"Gaia","mag":7.7128,"color":"#fff2c8","note":"Gaia DR3; distancia estimada amb paral.laxi"},{"name":"Gaia DR3 6254034065919830656","sourceId":"6254034065919830656","ra":235.4799198,"dec":-19.4628093,"distancePc":62.9433,"spectral":"Gaia","mag":7.9106,"color":"#fff2c8","note":"Gaia DR3; distancia estimada amb paral.laxi"},{"name":"Gaia DR3 6040263338761097984","sourceId":"6040263338761097984","ra":239.3233484,"dec":-29.9964443,"distancePc":66.21521,"spectral":"Gaia","mag":7.9303,"color":"#fff2c8","note":"Gaia DR3; distancia estimada amb paral.laxi"}]}
