{"id":"cube_2_-1_3","label":"Gaia DR3 cube 2_-1_3","epoch":"J2016.0","source":"Gaia DR3 gaia_source; filtrat per paral.laxi fiable i magnitud G","stars":[{"name":"Gaia DR3 1942451431236802816","sourceId":"1942451431236802816","ra":349.8743477,"dec":48.6255567,"distancePc":87.85147,"spectral":"Gaia","mag":5.1633,"color":"#ffd29a","note":"Gaia DR3; distancia estimada amb paral.laxi"},{"name":"Gaia DR3 1938019364284576000","sourceId":"1938019364284576000","ra":349.3201088,"dec":45.1638904,"distancePc":84.70372,"spectral":"Gaia","mag":6.1692,"color":"#ffd29a","note":"Gaia DR3; distancia estimada amb paral.laxi"},{"name":"Gaia DR3 2013264687356975360","sourceId":"2013264687356975360","ra":345.8395692,"dec":58.5638104,"distancePc":86.77289,"spectral":"Gaia","mag":6.2064,"color":"#ffd29a","note":"Gaia DR3; distancia estimada amb paral.laxi"},{"name":"Gaia DR3 1999373560527312640","sourceId":"1999373560527312640","ra":357.299966,"dec":58.9631634,"distancePc":81.43629,"spectral":"Gaia","mag":6.2579,"color":"#fff2c8","note":"Gaia DR3; distancia estimada amb paral.laxi"},{"name":"Gaia DR3 1989826535427047808","sourceId":"1989826535427047808","ra":339.8938548,"dec":51.1558672,"distancePc":82.52685,"spectral":"Gaia","mag":6.6896,"color":"#fff2c8","note":"Gaia DR3; distancia estimada amb paral.laxi"},{"name":"Gaia DR3 2006945038121202944","sourceId":"2006945038121202944","ra":340.8153258,"dec":56.4085089,"distancePc":83.18906,"spectral":"Gaia","mag":6.8515,"color":"#fff2c8","note":"Gaia DR3; distancia estimada amb paral.laxi"},{"name":"Gaia DR3 1998366132996941952","sourceId":"1998366132996941952","ra":358.8126045,"dec":58.0894271,"distancePc":80.02518,"spectral":"Gaia","mag":7.0812,"color":"#ffd29a","note":"Gaia DR3; distancia estimada amb paral.laxi"},{"name":"Gaia DR3 1989870653331591552","sourceId":"1989870653331591552","ra":340.0735971,"dec":51.5478485,"distancePc":85.53224,"spectral":"Gaia","mag":7.3385,"color":"#fff2c8","note":"Gaia DR3; distancia estimada amb paral.laxi"},{"name":"Gaia DR3 1989892471762844160","sourceId":"1989892471762844160","ra":341.0822087,"dec":51.4499332,"distancePc":80.27285,"spectral":"Gaia","mag":7.3762,"color":"#fff2c8","note":"Gaia DR3; distancia estimada amb paral.laxi"},{"name":"Gaia DR3 1990318493859331072","sourceId":"1990318493859331072","ra":342.7659138,"dec":52.2681951,"distancePc":94.70603,"spectral":"Gaia","mag":7.3765,"color":"#fff2c8","note":"Gaia DR3; distancia estimada amb paral.laxi"},{"name":"Gaia DR3 1991693437445859840","sourceId":"1991693437445859840","ra":352.8329404,"dec":52.4105637,"distancePc":85.72066,"spectral":"Gaia","mag":7.4696,"color":"#fff2c8","note":"Gaia DR3; distancia estimada amb paral.laxi"},{"name":"Gaia DR3 1995929679646711936","sourceId":"1995929679646711936","ra":351.7924553,"dec":54.8663696,"distancePc":76.36656,"spectral":"Gaia","mag":7.4738,"color":"#fff2c8","note":"Gaia DR3; distancia estimada amb paral.laxi"},{"name":"Gaia DR3 2012928271161549568","sourceId":"2012928271161549568","ra":356.324465,"dec":62.1723867,"distancePc":87.1213,"spectral":"Gaia","mag":7.7205,"color":"#ffd29a","note":"Gaia DR3; distancia estimada amb paral.laxi"},{"name":"Gaia DR3 2002700682715575680","sourceId":"2002700682715575680","ra":341.7258209,"dec":53.802742,"distancePc":97.87997,"spectral":"Gaia","mag":7.9128,"color":"#fff2c8","note":"Gaia DR3; distancia estimada amb paral.laxi"},{"name":"Gaia DR3 1990437825230931584","sourceId":"1990437825230931584","ra":342.9522667,"dec":53.1917068,"distancePc":99.12344,"spectral":"Gaia","mag":7.9589,"color":"#fff2c8","note":"Gaia DR3; distancia estimada amb paral.laxi"}]}
