{"id":"cube_-1_1_-2","label":"Gaia DR3 cube -1_1_-2","epoch":"J2016.0","source":"Gaia DR3 gaia_source; filtrat per paral.laxi fiable i magnitud G","stars":[{"name":"Gaia DR3 5502372732796307200","sourceId":"5502372732796307200","ra":97.8271125,"dec":-51.8254953,"distancePc":36.87082,"spectral":"Gaia","mag":5.4482,"color":"#fff2c8","note":"Gaia DR3; distancia estimada amb paral.laxi"},{"name":"Gaia DR3 5559704601966334848","sourceId":"5559704601966334848","ra":108.3853274,"dec":-44.6382726,"distancePc":56.20945,"spectral":"Gaia","mag":5.5181,"color":"#ff765f","note":"Gaia DR3; distancia estimada amb paral.laxi"},{"name":"Gaia DR3 5587574335515776000","sourceId":"5587574335515776000","ra":116.0399242,"dec":-36.0621252,"distancePc":43.98714,"spectral":"Gaia","mag":5.7189,"color":"#fff2c8","note":"Gaia DR3; distancia estimada amb paral.laxi"},{"name":"Gaia DR3 5492026740697659648","sourceId":"5492026740697659648","ra":110.0889923,"dec":-52.310875,"distancePc":34.92352,"spectral":"Gaia","mag":5.8991,"color":"#fff2c8","note":"Gaia DR3; distancia estimada amb paral.laxi"},{"name":"Gaia DR3 5605930166746409856","sourceId":"5605930166746409856","ra":108.0168119,"dec":-30.8212687,"distancePc":47.47819,"spectral":"Gaia","mag":6.0363,"color":"#fff2c8","note":"Gaia DR3; distancia estimada amb paral.laxi"},{"name":"Gaia DR3 5528565470596048256","sourceId":"5528565470596048256","ra":128.8026648,"dec":-39.9702585,"distancePc":36.16576,"spectral":"Gaia","mag":6.3118,"color":"#fff2c8","note":"Gaia DR3; distancia estimada amb paral.laxi"},{"name":"Gaia DR3 5574274952097988352","sourceId":"5574274952097988352","ra":96.7815899,"dec":-37.8953005,"distancePc":49.84197,"spectral":"Gaia","mag":6.399,"color":"#fff2c8","note":"Gaia DR3; distancia estimada amb paral.laxi"},{"name":"Gaia DR3 5328000290404075264","sourceId":"5328000290404075264","ra":132.0031688,"dec":-49.5751315,"distancePc":43.19337,"spectral":"Gaia","mag":6.6119,"color":"#fff2c8","note":"Gaia DR3; distancia estimada amb paral.laxi"},{"name":"Gaia DR3 5566892315632568704","sourceId":"5566892315632568704","ra":91.7484699,"dec":-46.2057483,"distancePc":47.22122,"spectral":"Gaia","mag":6.7353,"color":"#fff2c8","note":"Gaia DR3; distancia estimada amb paral.laxi"},{"name":"Gaia DR3 5504529287416164992","sourceId":"5504529287416164992","ra":104.439265,"dec":-52.6501307,"distancePc":36.96734,"spectral":"Gaia","mag":6.7887,"color":"#fff2c8","note":"Gaia DR3; distancia estimada amb paral.laxi"},{"name":"Gaia DR3 5591534810757825280","sourceId":"5591534810757825280","ra":111.7428284,"dec":-34.3117605,"distancePc":49.21978,"spectral":"Gaia","mag":6.9218,"color":"#fff2c8","note":"Gaia DR3; distancia estimada amb paral.laxi"},{"name":"Gaia DR3 5538573431596682496","sourceId":"5538573431596682496","ra":117.2047073,"dec":-38.2042619,"distancePc":42.45508,"spectral":"Gaia","mag":7.0223,"color":"#fff2c8","note":"Gaia DR3; distancia estimada amb paral.laxi"},{"name":"Gaia DR3 5554191685020871424","sourceId":"5554191685020871424","ra":91.1938186,"dec":-48.4583993,"distancePc":30.66243,"spectral":"Gaia","mag":7.0435,"color":"#ffd29a","note":"Gaia DR3; distancia estimada amb paral.laxi"},{"name":"Gaia DR3 5511491979160542464","sourceId":"5511491979160542464","ra":109.7330769,"dec":-45.2967578,"distancePc":46.51568,"spectral":"Gaia","mag":7.0499,"color":"#fff2c8","note":"Gaia DR3; distancia estimada amb paral.laxi"},{"name":"Gaia DR3 5579783574073770112","sourceId":"5579783574073770112","ra":103.0080634,"dec":-33.9152574,"distancePc":46.29855,"spectral":"Gaia","mag":7.0714,"color":"#fff2c8","note":"Gaia DR3; distancia estimada amb paral.laxi"},{"name":"Gaia DR3 5518807064384744832","sourceId":"5518807064384744832","ra":120.6116584,"dec":-46.3352835,"distancePc":36.38694,"spectral":"Gaia","mag":7.3688,"color":"#ffd29a","note":"Gaia DR3; distancia estimada amb paral.laxi"},{"name":"Gaia DR3 5504204553528873472","sourceId":"5504204553528873472","ra":109.5515057,"dec":-51.0511472,"distancePc":48.8044,"spectral":"Gaia","mag":7.3891,"color":"#fff2c8","note":"Gaia DR3; distancia estimada amb paral.laxi"},{"name":"Gaia DR3 5554191685019290368","sourceId":"5554191685019290368","ra":91.1946804,"dec":-48.4588395,"distancePc":30.79653,"spectral":"Gaia","mag":7.4208,"color":"#ffd29a","note":"Gaia DR3; distancia estimada amb paral.laxi"},{"name":"Gaia DR3 5508648676451080448","sourceId":"5508648676451080448","ra":108.8703732,"dec":-48.2292845,"distancePc":40.08669,"spectral":"Gaia","mag":7.528,"color":"#fff2c8","note":"Gaia DR3; distancia estimada amb paral.laxi"},{"name":"Gaia DR3 5534026023301322368","sourceId":"5534026023301322368","ra":119.9948768,"dec":-41.7044023,"distancePc":49.02109,"spectral":"Gaia","mag":7.5941,"color":"#fff2c8","note":"Gaia DR3; distancia estimada amb paral.laxi"},{"name":"Gaia DR3 5586184415378097792","sourceId":"5586184415378097792","ra":112.3807412,"dec":-38.1223606,"distancePc":53.00627,"spectral":"Gaia","mag":7.6131,"color":"#fff2c8","note":"Gaia DR3; distancia estimada amb paral.laxi"},{"name":"Gaia DR3 5525780373285137792","sourceId":"5525780373285137792","ra":132.2730086,"dec":-39.9538173,"distancePc":36.37984,"spectral":"Gaia","mag":7.6632,"color":"#ffd29a","note":"Gaia DR3; distancia estimada amb paral.laxi"},{"name":"Gaia DR3 5557384185753445504","sourceId":"5557384185753445504","ra":100.6123544,"dec":-42.5713163,"distancePc":52.90831,"spectral":"Gaia","mag":7.8982,"color":"#fff2c8","note":"Gaia DR3; distancia estimada amb paral.laxi"},{"name":"Gaia DR3 5318129356046433536","sourceId":"5318129356046433536","ra":129.3757359,"dec":-53.5913611,"distancePc":48.34932,"spectral":"Gaia","mag":7.967,"color":"#ffd29a","note":"Gaia DR3; distancia estimada amb paral.laxi"}]}
