{"id":"cube_0_-3_-2","label":"Gaia DR3 cube 0_-3_-2","epoch":"J2016.0","source":"Gaia DR3 gaia_source; filtrat per paral.laxi fiable i magnitud G","stars":[{"name":"Gaia DR3 6717240825593666304","sourceId":"6717240825593666304","ra":287.0876507,"dec":-40.4968191,"distancePc":56.63106,"spectral":"Gaia","mag":4.2492,"color":"#ffd29a","note":"Gaia DR3; distancia estimada amb paral.laxi"},{"name":"Gaia DR3 6730089817255923072","sourceId":"6730089817255923072","ra":280.9455952,"dec":-38.3236818,"distancePc":62.6877,"spectral":"Gaia","mag":5.0901,"color":"#e4f0ff","note":"Gaia DR3; distancia estimada amb paral.laxi"},{"name":"Gaia DR3 6772588591672712576","sourceId":"6772588591672712576","ra":290.1588809,"dec":-22.4024108,"distancePc":56.72739,"spectral":"Gaia","mag":5.5293,"color":"#fff2c8","note":"Gaia DR3; distancia estimada amb paral.laxi"},{"name":"Gaia DR3 4078295752276534144","sourceId":"4078295752276534144","ra":280.4652803,"dec":-23.8335434,"distancePc":61.69295,"spectral":"Gaia","mag":6.1805,"color":"#e4f0ff","note":"Gaia DR3; distancia estimada amb paral.laxi"},{"name":"Gaia DR3 4079819194344984832","sourceId":"4079819194344984832","ra":281.3278645,"dec":-21.0017503,"distancePc":59.61581,"spectral":"Gaia","mag":6.2407,"color":"#fff2c8","note":"Gaia DR3; distancia estimada amb paral.laxi"},{"name":"Gaia DR3 6759116997256065792","sourceId":"6759116997256065792","ra":287.6154878,"dec":-30.0074113,"distancePc":53.30007,"spectral":"Gaia","mag":6.4148,"color":"#fff2c8","note":"Gaia DR3; distancia estimada amb paral.laxi"},{"name":"Gaia DR3 6745887776423200768","sourceId":"6745887776423200768","ra":292.5626863,"dec":-32.0915682,"distancePc":51.38353,"spectral":"Gaia","mag":6.5073,"color":"#fff2c8","note":"Gaia DR3; distancia estimada amb paral.laxi"},{"name":"Gaia DR3 4048374845439879296","sourceId":"4048374845439879296","ra":279.2637179,"dec":-28.5136658,"distancePc":60.18609,"spectral":"Gaia","mag":6.521,"color":"#ffd29a","note":"Gaia DR3; distancia estimada amb paral.laxi"},{"name":"Gaia DR3 4047715482087935360","sourceId":"4047715482087935360","ra":276.670104,"dec":-30.3935749,"distancePc":48.28243,"spectral":"Gaia","mag":6.6295,"color":"#fff2c8","note":"Gaia DR3; distancia estimada amb paral.laxi"},{"name":"Gaia DR3 6728826963739348224","sourceId":"6728826963739348224","ra":281.246689,"dec":-39.7509121,"distancePc":57.529,"spectral":"Gaia","mag":6.6344,"color":"#fff2c8","note":"Gaia DR3; distancia estimada amb paral.laxi"},{"name":"Gaia DR3 4048089414733358208","sourceId":"4048089414733358208","ra":277.2996958,"dec":-29.2597378,"distancePc":47.95915,"spectral":"Gaia","mag":6.7749,"color":"#fff2c8","note":"Gaia DR3; distancia estimada amb paral.laxi"},{"name":"Gaia DR3 6763156018855811968","sourceId":"6763156018855811968","ra":288.4847451,"dec":-26.8766605,"distancePc":58.50348,"spectral":"Gaia","mag":7.0089,"color":"#fff2c8","note":"Gaia DR3; distancia estimada amb paral.laxi"},{"name":"Gaia DR3 4035756506416568960","sourceId":"4035756506416568960","ra":270.0766799,"dec":-39.2500413,"distancePc":58.64744,"spectral":"Gaia","mag":7.1399,"color":"#fff2c8","note":"Gaia DR3; distancia estimada amb paral.laxi"},{"name":"Gaia DR3 4062932688663275264","sourceId":"4062932688663275264","ra":271.5575179,"dec":-27.4928636,"distancePc":66.40354,"spectral":"Gaia","mag":7.1687,"color":"#fff2c8","note":"Gaia DR3; distancia estimada amb paral.laxi"},{"name":"Gaia DR3 6736604427984866176","sourceId":"6736604427984866176","ra":279.5825222,"dec":-32.6863826,"distancePc":69.24113,"spectral":"Gaia","mag":7.1921,"color":"#fff2c8","note":"Gaia DR3; distancia estimada amb paral.laxi"},{"name":"Gaia DR3 6741633731573703040","sourceId":"6741633731573703040","ra":294.6397658,"dec":-34.5495049,"distancePc":57.73487,"spectral":"Gaia","mag":7.2602,"color":"#fff2c8","note":"Gaia DR3; distancia estimada amb paral.laxi"},{"name":"Gaia DR3 6714760567878667264","sourceId":"6714760567878667264","ra":289.680608,"dec":-39.5481938,"distancePc":58.73511,"spectral":"Gaia","mag":7.3189,"color":"#fff2c8","note":"Gaia DR3; distancia estimada amb paral.laxi"},{"name":"Gaia DR3 6717992410510940928","sourceId":"6717992410510940928","ra":287.6996159,"dec":-38.9096306,"distancePc":60.40255,"spectral":"Gaia","mag":7.4942,"color":"#fff2c8","note":"Gaia DR3; distancia estimada amb paral.laxi"},{"name":"Gaia DR3 4075912835700087424","sourceId":"4075912835700087424","ra":279.2006331,"dec":-26.289626,"distancePc":52.98997,"spectral":"Gaia","mag":7.6593,"color":"#ffd29a","note":"Gaia DR3; distancia estimada amb paral.laxi"},{"name":"Gaia DR3 6745589980571162752","sourceId":"6745589980571162752","ra":290.7212369,"dec":-32.9208978,"distancePc":59.96426,"spectral":"Gaia","mag":7.6875,"color":"#fff2c8","note":"Gaia DR3; distancia estimada amb paral.laxi"},{"name":"Gaia DR3 6723032846710235392","sourceId":"6723032846710235392","ra":275.962974,"dec":-42.422827,"distancePc":58.67217,"spectral":"Gaia","mag":7.7171,"color":"#fff2c8","note":"Gaia DR3; distancia estimada amb paral.laxi"},{"name":"Gaia DR3 4075856039093376000","sourceId":"4075856039093376000","ra":278.0511063,"dec":-26.4970322,"distancePc":56.28295,"spectral":"Gaia","mag":7.8042,"color":"#fff2c8","note":"Gaia DR3; distancia estimada amb paral.laxi"},{"name":"Gaia DR3 4078516651023103360","sourceId":"4078516651023103360","ra":280.9278084,"dec":-22.6707533,"distancePc":64.16881,"spectral":"Gaia","mag":7.8713,"color":"#fff2c8","note":"Gaia DR3; distancia estimada amb paral.laxi"},{"name":"Gaia DR3 4052206673465161344","sourceId":"4052206673465161344","ra":273.6528032,"dec":-27.980342,"distancePc":61.58795,"spectral":"Gaia","mag":7.8842,"color":"#fff2c8","note":"Gaia DR3; distancia estimada amb paral.laxi"},{"name":"Gaia DR3 6733264558325897344","sourceId":"6733264558325897344","ra":277.2810578,"dec":-37.0098334,"distancePc":55.64181,"spectral":"Gaia","mag":7.8977,"color":"#fff2c8","note":"Gaia DR3; distancia estimada amb paral.laxi"},{"name":"Gaia DR3 4048023001773378944","sourceId":"4048023001773378944","ra":276.1106752,"dec":-29.5327656,"distancePc":48.00074,"spectral":"Gaia","mag":7.921,"color":"#fff2c8","note":"Gaia DR3; distancia estimada amb paral.laxi"}]}
