{"id":"cube_-2_3_-2","label":"Gaia DR3 cube -2_3_-2","epoch":"J2016.0","source":"Gaia DR3 gaia_source; filtrat per paral.laxi fiable i magnitud G","stars":[{"name":"Gaia DR3 5718613169236705536","sourceId":"5718613169236705536","ra":117.4219264,"dec":-17.2289292,"distancePc":78.77633,"spectral":"Gaia","mag":4.7614,"color":"#ff9f73","note":"Gaia DR3; distancia estimada amb paral.laxi"},{"name":"Gaia DR3 5610038148348975232","sourceId":"5610038148348975232","ra":108.7129654,"dec":-27.0381252,"distancePc":82.11925,"spectral":"Gaia","mag":5.2113,"color":"#ff9f73","note":"Gaia DR3; distancia estimada amb paral.laxi"},{"name":"Gaia DR3 5716535848180090624","sourceId":"5716535848180090624","ra":113.3316333,"dec":-19.4128378,"distancePc":91.07382,"spectral":"Gaia","mag":5.3287,"color":"#ffd29a","note":"Gaia DR3; distancia estimada amb paral.laxi"},{"name":"Gaia DR3 5712376704933582080","sourceId":"5712376704933582080","ra":117.9290499,"dec":-21.17351,"distancePc":89.08726,"spectral":"Gaia","mag":5.3633,"color":"#ffd29a","note":"Gaia DR3; distancia estimada amb paral.laxi"},{"name":"Gaia DR3 3031312261679398656","sourceId":"3031312261679398656","ra":109.0604265,"dec":-15.5857554,"distancePc":77.19815,"spectral":"Gaia","mag":5.442,"color":"#e4f0ff","note":"Gaia DR3; distancia estimada amb paral.laxi"},{"name":"Gaia DR3 3026832645147157760","sourceId":"3026832645147157760","ra":111.7832808,"dec":-17.8648564,"distancePc":89.98702,"spectral":"Gaia","mag":5.5595,"color":"#fff2c8","note":"Gaia DR3; distancia estimada amb paral.laxi"},{"name":"Gaia DR3 5615175066674756608","sourceId":"5615175066674756608","ra":113.2907119,"dec":-24.7106355,"distancePc":93.96354,"spectral":"Gaia","mag":5.8278,"color":"#e4f0ff","note":"Gaia DR3; distancia estimada amb paral.laxi"},{"name":"Gaia DR3 3029552046640275584","sourceId":"3029552046640275584","ra":116.3713485,"dec":-14.6906247,"distancePc":85.33621,"spectral":"Gaia","mag":6.0616,"color":"#e4f0ff","note":"Gaia DR3; distancia estimada amb paral.laxi"},{"name":"Gaia DR3 3029552115358950528","sourceId":"3029552115358950528","ra":116.3696922,"dec":-14.6862504,"distancePc":85.53629,"spectral":"Gaia","mag":6.8069,"color":"#fff2c8","note":"Gaia DR3; distancia estimada amb paral.laxi"},{"name":"Gaia DR3 5615963931909123584","sourceId":"5615963931909123584","ra":115.4401283,"dec":-22.4038264,"distancePc":79.77638,"spectral":"Gaia","mag":6.846,"color":"#fff2c8","note":"Gaia DR3; distancia estimada amb paral.laxi"},{"name":"Gaia DR3 3026965205016420224","sourceId":"3026965205016420224","ra":112.3351017,"dec":-17.3450018,"distancePc":79.36961,"spectral":"Gaia","mag":7.0128,"color":"#ffd29a","note":"Gaia DR3; distancia estimada amb paral.laxi"},{"name":"Gaia DR3 5698657651676371456","sourceId":"5698657651676371456","ra":119.8324871,"dec":-23.9491881,"distancePc":86.86021,"spectral":"Gaia","mag":7.6262,"color":"#ffd29a","note":"Gaia DR3; distancia estimada amb paral.laxi"},{"name":"Gaia DR3 5712011529634056448","sourceId":"5712011529634056448","ra":116.3040797,"dec":-22.2205791,"distancePc":88.49852,"spectral":"Gaia","mag":7.735,"color":"#ffd29a","note":"Gaia DR3; distancia estimada amb paral.laxi"},{"name":"Gaia DR3 5616318833643776640","sourceId":"5616318833643776640","ra":109.44566,"dec":-25.9855497,"distancePc":80.9494,"spectral":"Gaia","mag":7.744,"color":"#fff2c8","note":"Gaia DR3; distancia estimada amb paral.laxi"}]}
